reasoner/__init__.py
reasoner/auth.py
reasoner/cli.py
reasoner/config.py
reasoner/indexes.py
reasoner/reasoner.py
reasoner/registry.py
reasoner/sdk_updater.py
reasoner/traces.py
reasonercli-0.9.0.dist-info/METADATA
reasonercli-0.9.0.dist-info/WHEEL
reasonercli-0.9.0.dist-info/entry_points.txt
reasonercli-0.9.0.dist-info/licenses/LICENSE
reasonercli-0.9.0.dist-info/RECORD
