Metadata-Version: 2.4
Name: reasonercli
Version: 0.9.0
License-Expression: MIT
License-File: LICENSE
Classifier: License :: OSI Approved :: MIT License
Classifier: Operating System :: OS Independent
Classifier: Programming Language :: Python :: 3
Requires-Python: >=3.8
Requires-Dist: aiofiles>=24.1.0
Requires-Dist: httpimport>=1.4.0
Requires-Dist: httpx>=0.24.1
Requires-Dist: starlette>=0.29.0
Requires-Dist: typer[all]
